upir/__init__.py
upir/core/__init__.py
upir/core/architecture.py
upir/core/evidence.py
upir/core/specification.py
upir/core/temporal.py
upir/core/upir.py
upir/learning/__init__.py
upir/learning/learner.py
upir/learning/ppo.py
upir/patterns/__init__.py
upir/patterns/extractor.py
upir/patterns/library.py
upir/patterns/pattern.py
upir/synthesis/__init__.py
upir/synthesis/cegis.py
upir/synthesis/sketch.py
upir/verification/__init__.py
upir/verification/solver.py
upir/verification/verifier.py
upir-0.1.0.dist-info/licenses/LICENSE
upir-0.1.0.dist-info/METADATA
upir-0.1.0.dist-info/WHEEL
upir-0.1.0.dist-info/top_level.txt
upir-0.1.0.dist-info/RECORD
