Metadata-Version: 2.4
Name: upir
Version: 0.1.0
Summary: Universal Plan Intermediate Representation - Formal verification, synthesis, and optimization for distributed systems
Home-page: https://github.com/bassrehab/upir
Author: Subhadip Mitra
Author-email: Subhadip Mitra <contact@subhadipmitra.com>
Maintainer-email: Subhadip Mitra <contact@subhadipmitra.com>
License: Apache-2.0
Project-URL: Homepage, https://github.com/bassrehab/upir
Project-URL: Documentation, https://upir.subhadipmitra.com
Project-URL: Repository, https://github.com/bassrehab/upir
Project-URL: Issues, https://github.com/bassrehab/upir/issues
Project-URL: Changelog, https://github.com/bassrehab/upir/blob/main/CHANGELOG.md
Keywords: formal-verification,program-synthesis,distributed-systems,smt,cegis,reinforcement-learning,architecture
Classifier: Development Status :: 3 - Alpha
Classifier: Intended Audience :: Developers
Classifier: Intended Audience :: Science/Research
Classifier: License :: OSI Approved :: Apache Software License
Classifier: Operating System :: OS Independent
Classifier: Programming Language :: Python :: 3
Classifier: Programming Language :: Python :: 3.9
Classifier: Programming Language :: Python :: 3.10
Classifier: Programming Language :: Python :: 3.11
Classifier: Programming Language :: Python :: 3.12
Classifier: Topic :: Scientific/Engineering :: Artificial Intelligence
Classifier: Topic :: Software Development :: Code Generators
Classifier: Topic :: System :: Distributed Computing
Requires-Python: >=3.9
License-File: LICENSE
Requires-Dist: z3-solver>=4.12.2
Requires-Dist: numpy<2.0.0,>=1.24.3
Requires-Dist: scikit-learn<2.0.0,>=1.3.0
Provides-Extra: gcp
Requires-Dist: google-cloud-bigquery>=3.11.0; extra == "gcp"
Requires-Dist: google-cloud-pubsub>=2.18.0; extra == "gcp"
Requires-Dist: google-cloud-storage>=2.10.0; extra == "gcp"
Provides-Extra: dev
Requires-Dist: pytest>=7.4.0; extra == "dev"
Requires-Dist: pytest-cov>=4.1.0; extra == "dev"
Requires-Dist: mypy>=1.5.0; extra == "dev"
Requires-Dist: black>=23.7.0; extra == "dev"
Requires-Dist: isort>=5.12.0; extra == "dev"
Requires-Dist: ruff>=0.0.285; extra == "dev"
Requires-Dist: types-setuptools; extra == "dev"
Provides-Extra: docs
Requires-Dist: mkdocs>=1.5.0; extra == "docs"
Requires-Dist: mkdocs-material>=9.1.0; extra == "docs"
Requires-Dist: mkdocstrings[python]>=0.22.0; extra == "docs"
Provides-Extra: all
Requires-Dist: upir[dev,docs,gcp]; extra == "all"
Dynamic: author
Dynamic: home-page
Dynamic: license-file
Dynamic: requires-python
